{
  "tees": [],
  "holes": [
    {
      "ref": 1,
      "line": [
        [
          50.461454,
          7.18353
        ],
        [
          50.460818,
          7.183385
        ]
      ]
    },
    {
      "ref": 2,
      "line": [
        [
          50.461261,
          7.181846
        ],
        [
          50.460838,
          7.182804
        ],
        [
          50.460551,
          7.183059
        ],
        [
          50.460304,
          7.182968
        ]
      ]
    },
    {
      "ref": 3,
      "line": [
        [
          50.460895,
          7.182263
        ],
        [
          50.46067,
          7.182494
        ],
        [
          50.460435,
          7.182658
        ],
        [
          50.460215,
          7.182701
        ]
      ]
    },
    {
      "ref": 4,
      "line": [
        [
          50.460001,
          7.182444
        ],
        [
          50.46017,
          7.182421
        ],
        [
          50.460546,
          7.182195
        ],
        [
          50.46091,
          7.181889
        ],
        [
          50.461294,
          7.181395
        ]
      ]
    },
    {
      "ref": 5,
      "line": [
        [
          50.461587,
          7.18084
        ],
        [
          50.46141,
          7.180856
        ],
        [
          50.460778,
          7.181371
        ],
        [
          50.460082,
          7.182212
        ]
      ]
    },
    {
      "ref": 6,
      "line": [
        [
          50.459813,
          7.182107
        ],
        [
          50.460135,
          7.181553
        ]
      ]
    },
    {
      "ref": 7,
      "line": [
        [
          50.460286,
          7.18122
        ],
        [
          50.460872,
          7.180905
        ]
      ]
    },
    {
      "ref": 8,
      "line": [
        [
          50.460382,
          7.18073
        ],
        [
          50.461051,
          7.180434
        ],
        [
          50.461506,
          7.180628
        ]
      ]
    },
    {
      "ref": 9,
      "line": [
        [
          50.461746,
          7.180295
        ],
        [
          50.461738,
          7.180834
        ],
        [
          50.461656,
          7.181329
        ],
        [
          50.461324,
          7.182707
        ],
        [
          50.461446,
          7.183306
        ]
      ]
    },
    {
      "ref": 10,
      "line": [
        [
          50.461557,
          7.182831
        ],
        [
          50.462001,
          7.181069
        ],
        [
          50.462022,
          7.180986
        ]
      ]
    },
    {
      "ref": 11,
      "line": [
        [
          50.461222,
          7.180131
        ],
        [
          50.461929,
          7.179404
        ],
        [
          50.462317,
          7.178658
        ],
        [
          50.462635,
          7.178766
        ]
      ]
    },
    {
      "ref": 12,
      "line": [
        [
          50.462333,
          7.179055
        ],
        [
          50.461878,
          7.180608
        ]
      ]
    },
    {
      "ref": 13,
      "line": [
        [
          50.462074,
          7.180704
        ],
        [
          50.46235,
          7.179687
        ],
        [
          50.462837,
          7.178886
        ]
      ]
    },
    {
      "ref": 14,
      "line": [
        [
          50.462827,
          7.179164
        ],
        [
          50.462352,
          7.18084
        ]
      ]
    },
    {
      "ref": 15,
      "line": [
        [
          50.462857,
          7.181218
        ],
        [
          50.46327,
          7.179635
        ]
      ]
    },
    {
      "ref": 16,
      "line": [
        [
          50.463318,
          7.179179
        ],
        [
          50.463577,
          7.179568
        ],
        [
          50.463249,
          7.181437
        ]
      ]
    },
    {
      "ref": 17,
      "line": [
        [
          50.462966,
          7.181699
        ],
        [
          50.462731,
          7.183446
        ]
      ]
    },
    {
      "ref": 18,
      "line": [
        [
          50.462604,
          7.183732
        ],
        [
          50.462594,
          7.182765
        ]
      ]
    }
  ],
  "water": [
    {
      "ring": [
        [
          50.462154,
          7.18253
        ],
        [
          50.462157,
          7.182571
        ],
        [
          50.462123,
          7.182676
        ],
        [
          50.462107,
          7.182707
        ],
        [
          50.462086,
          7.182707
        ],
        [
          50.462071,
          7.182677
        ],
        [
          50.462028,
          7.182678
        ],
        [
          50.462009,
          7.182625
        ],
        [
          50.46202,
          7.182526
        ],
        [
          50.462037,
          7.182503
        ],
        [
          50.462072,
          7.182492
        ],
        [
          50.462134,
          7.182508
        ],
        [
          50.462154,
          7.18253
        ]
      ]
    }
  ],
  "woods": [],
  "greens": [
    {
      "ring": [
        [
          50.460798,
          7.183463
        ],
        [
          50.460816,
          7.183469
        ],
        [
          50.460834,
          7.183466
        ],
        [
          50.46085,
          7.183454
        ],
        [
          50.460863,
          7.183434
        ],
        [
          50.460872,
          7.183409
        ],
        [
          50.460874,
          7.183381
        ],
        [
          50.46087,
          7.183353
        ],
        [
          50.460861,
          7.183329
        ],
        [
          50.460848,
          7.183311
        ],
        [
          50.460831,
          7.1833
        ],
        [
          50.460814,
          7.183298
        ],
        [
          50.460796,
          7.183306
        ],
        [
          50.460782,
          7.183321
        ],
        [
          50.460771,
          7.183344
        ],
        [
          50.460765,
          7.18337
        ],
        [
          50.460766,
          7.183399
        ],
        [
          50.460772,
          7.183426
        ],
        [
          50.460783,
          7.183448
        ],
        [
          50.460798,
          7.183463
        ]
      ]
    },
    {
      "ring": [
        [
          50.46025,
          7.182902
        ],
        [
          50.460267,
          7.182878
        ],
        [
          50.460288,
          7.182864
        ],
        [
          50.460311,
          7.182862
        ],
        [
          50.460333,
          7.182872
        ],
        [
          50.460351,
          7.182892
        ],
        [
          50.460365,
          7.182921
        ],
        [
          50.460371,
          7.182956
        ],
        [
          50.46037,
          7.182992
        ],
        [
          50.460362,
          7.183025
        ],
        [
          50.460347,
          7.183051
        ],
        [
          50.460328,
          7.183069
        ],
        [
          50.460306,
          7.183076
        ],
        [
          50.460284,
          7.183072
        ],
        [
          50.460264,
          7.183057
        ],
        [
          50.460248,
          7.183032
        ],
        [
          50.460238,
          7.183001
        ],
        [
          50.460235,
          7.182967
        ],
        [
          50.460239,
          7.182932
        ],
        [
          50.46025,
          7.182902
        ]
      ]
    },
    {
      "ring": [
        [
          50.460157,
          7.182741
        ],
        [
          50.460152,
          7.182708
        ],
        [
          50.460154,
          7.182674
        ],
        [
          50.460163,
          7.182644
        ],
        [
          50.460178,
          7.18262
        ],
        [
          50.460198,
          7.182606
        ],
        [
          50.460219,
          7.182602
        ],
        [
          50.46024,
          7.18261
        ],
        [
          50.460258,
          7.182629
        ],
        [
          50.46027,
          7.182653
        ],
        [
          50.460277,
          7.182683
        ],
        [
          50.460278,
          7.182714
        ],
        [
          50.460272,
          7.182743
        ],
        [
          50.460261,
          7.182769
        ],
        [
          50.460246,
          7.182788
        ],
        [
          50.460227,
          7.182799
        ],
        [
          50.460206,
          7.1828
        ],
        [
          50.460185,
          7.182789
        ],
        [
          50.460168,
          7.182769
        ],
        [
          50.460157,
          7.182741
        ]
      ]
    },
    {
      "ring": [
        [
          50.461234,
          7.1814
        ],
        [
          50.461239,
          7.18137
        ],
        [
          50.461249,
          7.181345
        ],
        [
          50.461265,
          7.181327
        ],
        [
          50.461283,
          7.181318
        ],
        [
          50.461303,
          7.18132
        ],
        [
          50.46132,
          7.181331
        ],
        [
          50.461335,
          7.181351
        ],
        [
          50.461344,
          7.181375
        ],
        [
          50.461348,
          7.181404
        ],
        [
          50.461346,
          7.181432
        ],
        [
          50.461338,
          7.181458
        ],
        [
          50.461326,
          7.181479
        ],
        [
          50.461309,
          7.181493
        ],
        [
          50.461292,
          7.181498
        ],
        [
          50.461273,
          7.181493
        ],
        [
          50.461256,
          7.18148
        ],
        [
          50.461243,
          7.181458
        ],
        [
          50.461235,
          7.18143
        ],
        [
          50.461234,
          7.1814
        ]
      ]
    },
    {
      "ring": [
        [
          50.460059,
          7.182141
        ],
        [
          50.460074,
          7.182133
        ],
        [
          50.46009,
          7.182134
        ],
        [
          50.460105,
          7.182143
        ],
        [
          50.460117,
          7.182159
        ],
        [
          50.460125,
          7.18218
        ],
        [
          50.460129,
          7.182204
        ],
        [
          50.460127,
          7.182229
        ],
        [
          50.46012,
          7.182251
        ],
        [
          50.460109,
          7.182269
        ],
        [
          50.460095,
          7.182281
        ],
        [
          50.46008,
          7.182284
        ],
        [
          50.460064,
          7.182279
        ],
        [
          50.46005,
          7.182267
        ],
        [
          50.46004,
          7.182249
        ],
        [
          50.460034,
          7.182226
        ],
        [
          50.460033,
          7.182201
        ],
        [
          50.460037,
          7.182177
        ],
        [
          50.460046,
          7.182156
        ],
        [
          50.460059,
          7.182141
        ]
      ]
    },
    {
      "ring": [
        [
          50.460151,
          7.181643
        ],
        [
          50.46017,
          7.18163
        ],
        [
          50.460185,
          7.181608
        ],
        [
          50.460195,
          7.181579
        ],
        [
          50.460199,
          7.181547
        ],
        [
          50.460195,
          7.181515
        ],
        [
          50.460186,
          7.181486
        ],
        [
          50.46017,
          7.181463
        ],
        [
          50.460151,
          7.181449
        ],
        [
          50.46013,
          7.181446
        ],
        [
          50.460109,
          7.181454
        ],
        [
          50.460091,
          7.181473
        ],
        [
          50.460079,
          7.181499
        ],
        [
          50.460072,
          7.181531
        ],
        [
          50.460072,
          7.181565
        ],
        [
          50.460079,
          7.181596
        ],
        [
          50.460093,
          7.181621
        ],
        [
          50.46011,
          7.181639
        ],
        [
          50.46013,
          7.181646
        ],
        [
          50.460151,
          7.181643
        ]
      ]
    },
    {
      "ring": [
        [
          50.460871,
          7.180982
        ],
        [
          50.460886,
          7.180982
        ],
        [
          50.460901,
          7.180973
        ],
        [
          50.460913,
          7.180958
        ],
        [
          50.460922,
          7.180937
        ],
        [
          50.460925,
          7.180913
        ],
        [
          50.460923,
          7.180888
        ],
        [
          50.460917,
          7.180866
        ],
        [
          50.460906,
          7.180849
        ],
        [
          50.460892,
          7.180838
        ],
        [
          50.460877,
          7.180835
        ],
        [
          50.460862,
          7.180839
        ],
        [
          50.460848,
          7.180851
        ],
        [
          50.460838,
          7.180869
        ],
        [
          50.460832,
          7.180891
        ],
        [
          50.460831,
          7.180915
        ],
        [
          50.460835,
          7.180938
        ],
        [
          50.460843,
          7.180959
        ],
        [
          50.460856,
          7.180974
        ],
        [
          50.460871,
          7.180982
        ]
      ]
    },
    {
      "ring": [
        [
          50.461487,
          7.180687
        ],
        [
          50.4615,
          7.180699
        ],
        [
          50.461515,
          7.180703
        ],
        [
          50.46153,
          7.180698
        ],
        [
          50.461543,
          7.180686
        ],
        [
          50.461553,
          7.180668
        ],
        [
          50.461558,
          7.180645
        ],
        [
          50.461558,
          7.180621
        ],
        [
          50.461553,
          7.180601
        ],
        [
          50.461545,
          7.180584
        ],
        [
          50.461534,
          7.180572
        ],
        [
          50.461521,
          7.180566
        ],
        [
          50.461507,
          7.180566
        ],
        [
          50.461495,
          7.180573
        ],
        [
          50.461484,
          7.180586
        ],
        [
          50.461476,
          7.180603
        ],
        [
          50.461472,
          7.180623
        ],
        [
          50.461472,
          7.180647
        ],
        [
          50.461477,
          7.180669
        ],
        [
          50.461487,
          7.180687
        ]
      ]
    },
    {
      "ring": [
        [
          50.46262,
          7.178832
        ],
        [
          50.462634,
          7.178836
        ],
        [
          50.462648,
          7.178833
        ],
        [
          50.46266,
          7.178824
        ],
        [
          50.46267,
          7.178808
        ],
        [
          50.462676,
          7.178789
        ],
        [
          50.462677,
          7.178767
        ],
        [
          50.462674,
          7.178746
        ],
        [
          50.462667,
          7.178727
        ],
        [
          50.462657,
          7.178713
        ],
        [
          50.462644,
          7.178706
        ],
        [
          50.46263,
          7.178705
        ],
        [
          50.462616,
          7.178711
        ],
        [
          50.462605,
          7.178724
        ],
        [
          50.462597,
          7.178742
        ],
        [
          50.462593,
          7.178763
        ],
        [
          50.462594,
          7.178784
        ],
        [
          50.462599,
          7.178805
        ],
        [
          50.462608,
          7.178821
        ],
        [
          50.46262,
          7.178832
        ]
      ]
    },
    {
      "ring": [
        [
          50.461844,
          7.180671
        ],
        [
          50.461858,
          7.180684
        ],
        [
          50.461874,
          7.180688
        ],
        [
          50.461891,
          7.180684
        ],
        [
          50.461905,
          7.180671
        ],
        [
          50.461916,
          7.180653
        ],
        [
          50.461923,
          7.180629
        ],
        [
          50.461924,
          7.180603
        ],
        [
          50.46192,
          7.180579
        ],
        [
          50.461911,
          7.180557
        ],
        [
          50.461898,
          7.180542
        ],
        [
          50.461883,
          7.180534
        ],
        [
          50.461867,
          7.180534
        ],
        [
          50.461851,
          7.180542
        ],
        [
          50.461838,
          7.180557
        ],
        [
          50.461829,
          7.180578
        ],
        [
          50.461825,
          7.180603
        ],
        [
          50.461826,
          7.180629
        ],
        [
          50.461833,
          7.180652
        ],
        [
          50.461844,
          7.180671
        ]
      ]
    },
    {
      "ring": [
        [
          50.462847,
          7.178967
        ],
        [
          50.462863,
          7.178959
        ],
        [
          50.462876,
          7.178942
        ],
        [
          50.462885,
          7.17892
        ],
        [
          50.46289,
          7.178894
        ],
        [
          50.462888,
          7.178867
        ],
        [
          50.462882,
          7.178843
        ],
        [
          50.462871,
          7.178823
        ],
        [
          50.462855,
          7.17881
        ],
        [
          50.462838,
          7.178805
        ],
        [
          50.462821,
          7.178809
        ],
        [
          50.462806,
          7.178822
        ],
        [
          50.462794,
          7.178842
        ],
        [
          50.462787,
          7.178868
        ],
        [
          50.462786,
          7.178895
        ],
        [
          50.462791,
          7.178921
        ],
        [
          50.4628,
          7.178943
        ],
        [
          50.462814,
          7.178959
        ],
        [
          50.46283,
          7.178968
        ],
        [
          50.462847,
          7.178967
        ]
      ]
    },
    {
      "ring": [
        [
          50.462308,
          7.18079
        ],
        [
          50.462321,
          7.180769
        ],
        [
          50.462339,
          7.180755
        ],
        [
          50.462359,
          7.180752
        ],
        [
          50.462378,
          7.18076
        ],
        [
          50.462394,
          7.180777
        ],
        [
          50.462405,
          7.1808
        ],
        [
          50.46241,
          7.180826
        ],
        [
          50.462411,
          7.180854
        ],
        [
          50.462405,
          7.180881
        ],
        [
          50.462395,
          7.180904
        ],
        [
          50.462381,
          7.180921
        ],
        [
          50.462364,
          7.18093
        ],
        [
          50.462346,
          7.18093
        ],
        [
          50.462329,
          7.180921
        ],
        [
          50.462314,
          7.180904
        ],
        [
          50.462303,
          7.180879
        ],
        [
          50.462298,
          7.180849
        ],
        [
          50.462299,
          7.180819
        ],
        [
          50.462308,
          7.18079
        ]
      ]
    },
    {
      "ring": [
        [
          50.463289,
          7.181517
        ],
        [
          50.463303,
          7.181498
        ],
        [
          50.463312,
          7.181474
        ],
        [
          50.463316,
          7.181446
        ],
        [
          50.463315,
          7.181418
        ],
        [
          50.463308,
          7.181391
        ],
        [
          50.463296,
          7.18137
        ],
        [
          50.463281,
          7.181355
        ],
        [
          50.463263,
          7.181348
        ],
        [
          50.463245,
          7.181351
        ],
        [
          50.463228,
          7.181362
        ],
        [
          50.463214,
          7.181381
        ],
        [
          50.463205,
          7.181405
        ],
        [
          50.463201,
          7.181433
        ],
        [
          50.463203,
          7.181461
        ],
        [
          50.46321,
          7.181487
        ],
        [
          50.463221,
          7.181508
        ],
        [
          50.463237,
          7.181523
        ],
        [
          50.463254,
          7.18153
        ],
        [
          50.463272,
          7.181527
        ],
        [
          50.463289,
          7.181517
        ]
      ]
    },
    {
      "ring": [
        [
          50.463242,
          7.179709
        ],
        [
          50.463257,
          7.179719
        ],
        [
          50.463274,
          7.179721
        ],
        [
          50.463291,
          7.179715
        ],
        [
          50.463305,
          7.179701
        ],
        [
          50.463316,
          7.17968
        ],
        [
          50.463321,
          7.179655
        ],
        [
          50.463322,
          7.179629
        ],
        [
          50.463317,
          7.179603
        ],
        [
          50.463307,
          7.17958
        ],
        [
          50.463292,
          7.179564
        ],
        [
          50.463275,
          7.179557
        ],
        [
          50.463257,
          7.179559
        ],
        [
          50.463241,
          7.17957
        ],
        [
          50.463228,
          7.179589
        ],
        [
          50.46322,
          7.179614
        ],
        [
          50.463217,
          7.179642
        ],
        [
          50.463221,
          7.179668
        ],
        [
          50.463229,
          7.179691
        ],
        [
          50.463242,
          7.179709
        ]
      ]
    },
    {
      "ring": [
        [
          50.462678,
          7.183455
        ],
        [
          50.462679,
          7.18343
        ],
        [
          50.462684,
          7.183406
        ],
        [
          50.462694,
          7.183386
        ],
        [
          50.462708,
          7.183373
        ],
        [
          50.462724,
          7.183368
        ],
        [
          50.46274,
          7.18337
        ],
        [
          50.462755,
          7.183382
        ],
        [
          50.462766,
          7.1834
        ],
        [
          50.462773,
          7.183422
        ],
        [
          50.462775,
          7.183446
        ],
        [
          50.462772,
          7.183471
        ],
        [
          50.462764,
          7.183492
        ],
        [
          50.462752,
          7.183509
        ],
        [
          50.462738,
          7.183518
        ],
        [
          50.462722,
          7.18352
        ],
        [
          50.462706,
          7.183514
        ],
        [
          50.462693,
          7.1835
        ],
        [
          50.462683,
          7.183479
        ],
        [
          50.462678,
          7.183455
        ]
      ]
    },
    {
      "ring": [
        [
          50.462567,
          7.182811
        ],
        [
          50.462559,
          7.182791
        ],
        [
          50.462555,
          7.182769
        ],
        [
          50.462557,
          7.182746
        ],
        [
          50.462563,
          7.182726
        ],
        [
          50.462573,
          7.18271
        ],
        [
          50.462586,
          7.1827
        ],
        [
          50.462601,
          7.182697
        ],
        [
          50.462615,
          7.182703
        ],
        [
          50.462626,
          7.182714
        ],
        [
          50.462635,
          7.18273
        ],
        [
          50.46264,
          7.18275
        ],
        [
          50.462641,
          7.182771
        ],
        [
          50.462637,
          7.182791
        ],
        [
          50.46263,
          7.182809
        ],
        [
          50.46262,
          7.182823
        ],
        [
          50.462606,
          7.182831
        ],
        [
          50.462592,
          7.182831
        ],
        [
          50.462578,
          7.182824
        ],
        [
          50.462567,
          7.182811
        ]
      ]
    },
    {
      "ring": [
        [
          50.461414,
          7.183361
        ],
        [
          50.461404,
          7.183343
        ],
        [
          50.461397,
          7.18332
        ],
        [
          50.461396,
          7.183295
        ],
        [
          50.4614,
          7.183271
        ],
        [
          50.461409,
          7.183251
        ],
        [
          50.461422,
          7.183236
        ],
        [
          50.461437,
          7.183228
        ],
        [
          50.461453,
          7.183229
        ],
        [
          50.461467,
          7.183237
        ],
        [
          50.461479,
          7.183252
        ],
        [
          50.461487,
          7.183273
        ],
        [
          50.461491,
          7.183296
        ],
        [
          50.46149,
          7.18332
        ],
        [
          50.461484,
          7.183342
        ],
        [
          50.461473,
          7.18336
        ],
        [
          50.46146,
          7.183372
        ],
        [
          50.461444,
          7.183377
        ],
        [
          50.461428,
          7.183373
        ],
        [
          50.461414,
          7.183361
        ]
      ]
    },
    {
      "ring": [
        [
          50.461954,
          7.180984
        ],
        [
          50.461956,
          7.180955
        ],
        [
          50.461964,
          7.180928
        ],
        [
          50.461977,
          7.180906
        ],
        [
          50.461993,
          7.180891
        ],
        [
          50.462012,
          7.180886
        ],
        [
          50.462031,
          7.180891
        ],
        [
          50.462048,
          7.180905
        ],
        [
          50.462062,
          7.180928
        ],
        [
          50.462069,
          7.180956
        ],
        [
          50.462071,
          7.180987
        ],
        [
          50.462066,
          7.181017
        ],
        [
          50.462055,
          7.181042
        ],
        [
          50.462039,
          7.181061
        ],
        [
          50.46202,
          7.18107
        ],
        [
          50.462001,
          7.181069
        ],
        [
          50.461983,
          7.181058
        ],
        [
          50.461968,
          7.181039
        ],
        [
          50.461958,
          7.181013
        ],
        [
          50.461954,
          7.180984
        ]
      ]
    }
  ],
  "bunkers": [],
  "fairways": []
}
